bing_search_mcp_wx/__init__.py
bing_search_mcp_wx/__main__.py
bing_search_mcp_wx/server.py
bing_search_mcp_wx-0.1.0.dist-info/METADATA
bing_search_mcp_wx-0.1.0.dist-info/WHEEL
bing_search_mcp_wx-0.1.0.dist-info/entry_points.txt
bing_search_mcp_wx-0.1.0.dist-info/licenses/LICENSE
bing_search_mcp_wx-0.1.0.dist-info/RECORD
