Metadata-Version: 2.4
Name: bing-search-mcp-wx
Version: 0.1.0
Summary: Mcp for Bing search with a given apiId
License-Expression: MIT
License-File: LICENSE
Requires-Python: >=3.10
Requires-Dist: mcp[cli]>=1.2.0
Requires-Dist: python-dotenv>=1.0.0
Requires-Dist: requests>=2.31.0
